looplm/__init__.py
looplm/chat/__init__.py
looplm/chat/compact_handler.py
looplm/chat/console.py
looplm/chat/control.py
looplm/chat/persistence.py
looplm/chat/prompt_manager.py
looplm/chat/session.py
looplm/chat/textual_ui.py
looplm/cli/__init__.py
looplm/cli/__main__.py
looplm/cli/main.py
looplm/cli/setup.py
looplm/commands/__init__.py
looplm/commands/custom_date_command.py
looplm/commands/file_command.py
looplm/commands/folder_command.py
looplm/commands/github_command.py
looplm/commands/image_command.py
looplm/commands/manager.py
looplm/commands/pdf_command.py
looplm/commands/processor.py
looplm/commands/registry.py
looplm/commands/shell_command.py
looplm/config/__init__.py
looplm/config/manager.py
looplm/config/providers.py
looplm/conversation/__init__.py
looplm/conversation/handler.py
looplm/prompts/compact.txt
looplm/tools/__init__.py
looplm/tools/base.py
looplm/tools/builtin/__init__.py
looplm/tools/builtin/bash_tool.py
looplm/tools/builtin/basic_tools.py
looplm/tools/manager.py
looplm/tools/registry.py
looplm/utils/prompts.py
looplm/utils/readline_compatibility.py
looplm/utils/sample.ipynb
looplm-0.4.14.dist-info/LICENSE
looplm-0.4.14.dist-info/METADATA
looplm-0.4.14.dist-info/WHEEL
looplm-0.4.14.dist-info/entry_points.txt
looplm-0.4.14.dist-info/RECORD
