Metadata-Version: 2.3
Name: looplm
Version: 0.4.14
Summary: Loop-LM: Tool to access LLMs from the command line
Author: Chaitanya Devaguptapu
Author-email: tdchaitanya@gmail.com
Requires-Python: >=3.10,<4.0
Classifier: Programming Language :: Python :: 3
Classifier: Programming Language :: Python :: 3.10
Classifier: Programming Language :: Python :: 3.11
Classifier: Programming Language :: Python :: 3.12
Classifier: Programming Language :: Python :: 3.13
Requires-Dist: aiofiles (>=24.1.0,<25.0.0)
Requires-Dist: aiohttp (>=3.11.14,<4.0.0)
Requires-Dist: boto3 (>=1.37.21,<2.0.0)
Requires-Dist: click (>=8.1.8,<9.0.0)
Requires-Dist: cryptography (>=44.0.2,<45.0.0)
Requires-Dist: gitingest (>=0.1.4,<0.2.0)
Requires-Dist: gnureadline (>=8.2.13,<9.0.0) ; sys_platform != "win32"
Requires-Dist: google-genai (>=1.8.0,<2.0.0)
Requires-Dist: litellm (>=1.64.1,<2.0.0)
Requires-Dist: markitdown (>=0.1.1,<0.2.0)
Requires-Dist: prompt-toolkit (>=3.0.50,<4.0.0)
Requires-Dist: pyperclip (>=1.9.0,<2.0.0)
Requires-Dist: pyreadline3 (>=3.4.1,<4.0.0) ; sys_platform == "win32"
Requires-Dist: requests (>=2.32.3,<3.0.0)
Requires-Dist: rich (>=13.9.4,<14.0.0)
Requires-Dist: textual (>=0.87.0,<0.88.0)
